huaweicloudsdkiam/__init__.py
huaweicloudsdkiam/v3/__init__.py
huaweicloudsdkiam/v3/iam_async_client.py
huaweicloudsdkiam/v3/iam_client.py
huaweicloudsdkiam/v3/iam_credentials.py
huaweicloudsdkiam/v3/model/__init__.py
huaweicloudsdkiam/v3/model/acl_policy_option.py
huaweicloudsdkiam/v3/model/acl_policy_result.py
huaweicloudsdkiam/v3/model/agency_all_project_role.py
huaweicloudsdkiam/v3/model/agency_assumedby.py
huaweicloudsdkiam/v3/model/agency_assumedby_user.py
huaweicloudsdkiam/v3/model/agency_assumedby_user_domain.py
huaweicloudsdkiam/v3/model/agency_auth.py
huaweicloudsdkiam/v3/model/agency_auth_identity.py
huaweicloudsdkiam/v3/model/agency_create_result.py
huaweicloudsdkiam/v3/model/agency_list_result.py
huaweicloudsdkiam/v3/model/agency_policy.py
huaweicloudsdkiam/v3/model/agency_policy_resource.py
huaweicloudsdkiam/v3/model/agency_policy_role_option.py
huaweicloudsdkiam/v3/model/agency_policy_role_result.py
huaweicloudsdkiam/v3/model/agency_policy_statement.py
huaweicloudsdkiam/v3/model/agency_show_result.py
huaweicloudsdkiam/v3/model/agency_token_assumerole.py
huaweicloudsdkiam/v3/model/agency_token_auth.py
huaweicloudsdkiam/v3/model/agency_token_domain.py
huaweicloudsdkiam/v3/model/agency_token_identity.py
huaweicloudsdkiam/v3/model/agency_token_project.py
huaweicloudsdkiam/v3/model/agency_token_project_domain.py
huaweicloudsdkiam/v3/model/agency_token_result.py
huaweicloudsdkiam/v3/model/agency_token_scope.py
huaweicloudsdkiam/v3/model/agency_token_scope_domain.py
huaweicloudsdkiam/v3/model/agency_token_scope_project.py
huaweicloudsdkiam/v3/model/agency_token_user.py
huaweicloudsdkiam/v3/model/agency_token_user_domain.py
huaweicloudsdkiam/v3/model/agency_update_result.py
huaweicloudsdkiam/v3/model/allow_address_netmasks_option.py
huaweicloudsdkiam/v3/model/allow_address_netmasks_option_i_pv6.py
huaweicloudsdkiam/v3/model/allow_address_netmasks_result.py
huaweicloudsdkiam/v3/model/allow_address_netmasks_result_i_pv6.py
huaweicloudsdkiam-3.1.184.dist-info/METADATA
huaweicloudsdkiam-3.1.184.dist-info/WHEEL
huaweicloudsdkiam-3.1.184.dist-info/licenses/LICENSE
huaweicloudsdkiam-3.1.184.dist-info/RECORD
